{
  "taskId": "260224-auto-40",
  "mode": "full",
  "pipeline": "spec_execute_verify",
  "startedAt": "2026-02-24T12:32:26.594Z",
  "updatedAt": "2026-02-24T12:49:22.999Z",
  "state": "running",
  "currentStage": "architect",
  "stages": {
    "taskify": {
      "state": "completed",
      "retries": 0,
      "startedAt": "2026-02-24T12:32:28.936Z",
      "outputFile": "task.json",
      "completedAt": "2026-02-24T12:34:14.048Z",
      "elapsed": 105112
    },
    "architect": {
      "state": "completed",
      "retries": 0,
      "startedAt": "2026-02-24T12:46:31.828Z",
      "outputFile": "plan.md",
      "completedAt": "2026-02-24T12:49:22.999Z",
      "elapsed": 171171
    }
  },
  "triggeredBy": "comment",
  "issueNumber": 567,
  "runId": "22350936251",
  "runUrl": "https://github.com/A-Guy-educ/A-Guy/actions/runs/22350936251"
}